medusae/VERSION
medusae/__init__.py
medusae-0.0.1.dist-info/LICENSE
medusae-0.0.1.dist-info/METADATA
medusae-0.0.1.dist-info/WHEEL
medusae-0.0.1.dist-info/top_level.txt
medusae-0.0.1.dist-info/RECORD
